[
    {
        "29-01-2018": {
            "min": {
                "Chl_a": 203.10773779517825,
                "Cya": 142.489920932452,
                "Turb": 17.423334234873806,
                "CDOM": 7.932041365059224,
                "DOC": 17.21824343295735,
                "Color": 37.49932550478021,
                "WQI": -0.3283019886444708
            },
            "max": {
                "Chl_a": 277.3149652586867,
                "Cya": 277.30578110907487,
                "Turb": 19.381922470034922,
                "CDOM": 9.775273864616572,
                "DOC": 20.200544131475667,
                "Color": 51.798888015551256,
                "WQI": -0.624838250471607
            },
            "mean": {
                "Chl_a": 263.48072073687035,
                "Cya": 190.30338024406433,
                "Turb": 19.0493546148884,
                "CDOM": 7.076757879767785,
                "DOC": 15.780004795700318,
                "Color": 31.435071806934538,
                "WQI": -0.4706098674857115
            },
            "stDev": {
                "Chl_a": 1437.9268997286606,
                "Cya": 0.6291905797474332,
                "Turb": 32.744417362606875,
                "CDOM": 8.601452928521784,
                "DOC": 18.3184771885852,
                "Color": 42.503526339413284,
                "WQI": -1.0526438133081422
            }
        }
    },
    {
        "08-02-2018": {
            "min": {
                "Chl_a": 519.6086515462819,
                "Cya": 475.86242627129735,
                "Turb": 23.83461604076614,
                "CDOM": 19.602195457034938,
                "DOC": 34.38571031961229,
                "Color": 151.88220181092532,
                "WQI": -1.0000001981537618
            },
            "max": {
                "Chl_a": 167.3166546190502,
                "Cya": 892.6315870698802,
                "Turb": 16.280070644415893,
                "CDOM": 20.047195085131875,
                "DOC": 34.980908553332945,
                "Color": 157.24593161534796,
                "WQI": -0.6500580290631374
            },
            "mean": {
                "Chl_a": 297.3790255595836,
                "Cya": 725.3718040795967,
                "Turb": 19.8429160407245,
                "CDOM": 18.96153471830346,
                "DOC": 33.52318325600256,
                "Color": 144.27634101298167,
                "WQI": -0.8118063138012915
            },
            "stDev": {
                "Chl_a": 6.4653362208782035,
                "Cya": 1.9121450174780183,
                "Turb": 3.5374250091624786,
                "CDOM": 53.11100869374609,
                "DOC": 73.67444105287731,
                "Color": 709.2047101611364,
                "WQI": -0.5652907742855047
            }
        }
    },
    {
        "10-03-2018": {
            "min": {
                "Chl_a": 438.62504433277513,
                "Cya": 473.705204924759,
                "Turb": 22.562423133518834,
                "CDOM": 26.720892020879102,
                "DOC": 43.57518975240752,
                "Color": 245.20282468953,
                "WQI": -0.8169939637496275
            },
            "max": {
                "Chl_a": 74.99951630433664,
                "Cya": 1562.5090972977657,
                "Turb": 12.102941368525784,
                "CDOM": 21.289094944660924,
                "DOC": 36.62582427235591,
                "Color": 172.55896051131714,
                "WQI": -0.42234833959659485
            },
            "mean": {
                "Chl_a": 155.7079463644211,
                "Cya": 1017.1114494037514,
                "Turb": 15.870088400953591,
                "CDOM": 21.42627579589471,
                "DOC": 36.806115806465414,
                "Color": 174.2810950072807,
                "WQI": -0.5068286716355628
            },
            "stDev": {
                "Chl_a": 23.644941315967188,
                "Cya": 8.868099273402878,
                "Turb": 7.406450202334823,
                "CDOM": 28.31759339658966,
                "DOC": 45.5521559133272,
                "Color": 268.22230700911035,
                "WQI": -0.4498106609685345
            }
        }
    },
    {
        "15-03-2018": {
            "min": {
                "Chl_a": 184.38463113757166,
                "Cya": 587.8265909809936,
                "Turb": 16.845919591040367,
                "CDOM": 20.976634347934564,
                "DOC": 36.21414374724272,
                "Color": 168.65901646557748,
                "WQI": -0.8195488953463701
            },
            "max": {
                "Chl_a": 176.39526235031448,
                "Cya": 880.1369335324804,
                "Turb": 16.58614556260709,
                "CDOM": 20.61549455095935,
                "DOC": 35.73652215710535,
                "Color": 164.19086371787452,
                "WQI": -0.7738620714780935
            },
            "mean": {
                "Chl_a": 200.36654689195993,
                "Cya": 721.5813071125132,
                "Turb": 17.341349044362882,
                "CDOM": 19.76143381770835,
                "DOC": 34.59905762158568,
                "Color": 153.7939974988011,
                "WQI": -0.8303314328560963
            },
            "stDev": {
                "Chl_a": 486.84060828951084,
                "Cya": 0.18361605465082836,
                "Turb": 23.33902709208746,
                "CDOM": 1.2513996459449093,
                "DOC": 4.196277411881941,
                "Color": 2.15818332839186,
                "WQI": -0.8599107369998626
            }
        }
    },
    {
        "20-03-2018": {
            "min": {
                "Chl_a": 102.0836661724919,
                "Cya": 528.7514366908475,
                "Turb": 13.608167654638105,
                "CDOM": 28.991808316762647,
                "DOC": 46.37900058471679,
                "Color": 278.15967981303106,
                "WQI": -0.32539669164680585
            },
            "max": {
                "Chl_a": 81.86158586581006,
                "Cya": 891.1196167268657,
                "Turb": 12.518460393378575,
                "CDOM": 28.19358253518256,
                "DOC": 45.39956909839751,
                "Color": 266.4084255064963,
                "WQI": -0.39811907491040815
            },
            "mean": {
                "Chl_a": 81.92020601022493,
                "Cya": 710.5956753649908,
                "Turb": 12.521896057336875,
                "CDOM": 24.920813295186775,
                "DOC": 41.31268196749743,
                "Color": 220.13890490566746,
                "WQI": -0.3215210501942039
            },
            "stDev": {
                "Chl_a": 16.673077318002036,
                "Cya": 0.2710639923115434,
                "Turb": 6.235806088175063,
                "CDOM": 12.17795280548569,
                "DOC": 23.89634771870858,
                "Color": 72.75889911095919,
                "WQI": -0.34570805088313206
            }
        }
    },
    {
        "30-03-2018": {
            "min": {
                "Chl_a": 211.8303755122873,
                "Cya": 116.84180646422436,
                "Turb": 17.678840772775512,
                "CDOM": 6.104432808690883,
                "DOC": 14.094000967584268,
                "Color": 25.01343945693554,
                "WQI": -0.2512820013176065
            },
            "max": {
                "Chl_a": 242.27719358494718,
                "Cya": 242.44881470474274,
                "Turb": 18.513379984723684,
                "CDOM": 8.771695421015657,
                "DOC": 18.595018995264123,
                "Color": 43.81115786304654,
                "WQI": -0.7128874324806308
            },
            "mean": {
                "Chl_a": 275.26592639237333,
                "Cya": 164.85173809591734,
                "Turb": 19.3334574674085,
                "CDOM": 5.669921341200103,
                "DOC": 13.3204203436282,
                "Color": 22.314822595287595,
                "WQI": -0.6060705895660699
            },
            "stDev": {
                "Chl_a": 310.25428130850133,
                "Cya": 0.1819062452252597,
                "Turb": 20.126641109839383,
                "CDOM": 16.414451959654695,
                "DOC": 30.022802114291316,
                "Color": 115.4351314268553,
                "WQI": -0.9240016300745522
            }
        }
    },
    {
        "04-04-2018": {
            "min": {
                "Chl_a": 105.62421596646367,
                "Cya": 162.21586002570226,
                "Turb": 13.781973437594846,
                "CDOM": 4.075510824688263,
                "DOC": 10.348841398173201,
                "Color": 13.393498332361993,
                "WQI": -0.35398215355381113
            },
            "max": {
                "Chl_a": 52.50012869613608,
                "Cya": 576.622315825019,
                "Turb": 10.502415516010295,
                "CDOM": 24.757560242320658,
                "DOC": 41.105620800556494,
                "Color": 217.91329922707772,
                "WQI": -0.41860471608281963
            },
            "mean": {
                "Chl_a": 131.94680132541862,
                "Cya": 178.7240691509855,
                "Turb": 14.953966510098937,
                "CDOM": 3.864357333997363,
                "DOC": 9.936375934605516,
                "Color": 12.33594188700442,
                "WQI": -0.49820125946593036
            },
            "stDev": {
                "Chl_a": 275.0190335256349,
                "Cya": 0.13440930369665213,
                "Turb": 19.327599666733878,
                "CDOM": 27.254640503736262,
                "DOC": 44.23907199568475,
                "Color": 252.81654380962297,
                "WQI": -0.8138867557494698
            }
        }
    },
    {
        "09-04-2018": {
            "min": {
                "Chl_a": 294.4825742779997,
                "Cya": 86.79288715698385,
                "Turb": 19.777829595447205,
                "CDOM": 1.4449285535759655,
                "DOC": 4.683902003269693,
                "Color": 2.695511920305829,
                "WQI": -0.5950415150541379
            },
            "max": {
                "Chl_a": 74.89930468457753,
                "Cya": 1572.356816612937,
                "Turb": 12.096666769057684,
                "CDOM": 29.676433199225553,
                "DOC": 47.21399107171737,
                "Color": 288.38044607464036,
                "WQI": -0.5374532093220861
            },
            "mean": {
                "Chl_a": 117.08437003801997,
                "Cya": 495.0035391689511,
                "Turb": 14.316302600756131,
                "CDOM": 12.469447961651209,
                "DOC": 24.332416667750962,
                "Color": 75.46904538846488,
                "WQI": -0.4459413190956136
            },
            "stDev": {
                "Chl_a": 10.524058491654285,
                "Cya": 46.83550434391886,
                "Turb": 4.84414961813756,
                "CDOM": 128.76941643171972,
                "DOC": 144.9996856463798,
                "Color": 2788.917414709147,
                "WQI": -0.398419648217685
            }
        }
    },
    {
        "14-04-2018": {
            "min": {
                "Chl_a": 486.77485879555206,
                "Cya": 156.66873957229672,
                "Turb": 23.33800800340727,
                "CDOM": 2.0316424710768595,
                "DOC": 6.077923833597923,
                "Color": 4.565220679808375,
                "WQI": -1.3149603458300918
            },
            "max": {
                "Chl_a": 238.54908463331446,
                "Cya": 262.6677383037551,
                "Turb": 18.415555676350188,
                "CDOM": 4.802525660159152,
                "DOC": 11.732525295614332,
                "Color": 17.262753800413154,
                "WQI": -0.8809523945285116
            },
            "mean": {
                "Chl_a": 354.0995189371552,
                "Cya": 196.70778541968556,
                "Turb": 21.03135781116847,
                "CDOM": 3.157991145509301,
                "DOC": 8.515430824509108,
                "Color": 9.028872569796489,
                "WQI": -1.0104553652192754
            },
            "stDev": {
                "Chl_a": 4.512582083624034,
                "Cya": 0.046757803897746295,
                "Turb": 2.6715100100794738,
                "CDOM": 31.925979920417095,
                "DOC": 49.926416839096674,
                "Color": 322.8692535796646,
                "WQI": -0.5445479067822204
            }
        }
    },
    {
        "24-04-2018": {
            "min": {
                "Chl_a": 195.74450209292843,
                "Cya": 82.95418146203146,
                "Turb": 17.201194400388097,
                "CDOM": 1.246555836708689,
                "DOC": 4.183854202630945,
                "Color": 2.145281524927778,
                "WQI": -0.4393304578459282
            },
            "max": {
                "Chl_a": 62.064192181826115,
                "Cya": 1684.0521524899668,
                "Turb": 11.235386273155292,
                "CDOM": 31.081001624576636,
                "DOC": 48.91302274032276,
                "Color": 309.75341650357393,
                "WQI": -0.4878705990156197
            },
            "mean": {
                "Chl_a": 80.33679410682613,
                "Cya": 565.2231952802251,
                "Turb": 12.428442069712435,
                "CDOM": 11.798105300820355,
                "DOC": 23.324395419340224,
                "Color": 69.28017964820424,
                "WQI": -0.3831142237084628
            },
            "stDev": {
                "Chl_a": 11.590948182304205,
                "Cya": 77.30373334008306,
                "Turb": 5.122874886219932,
                "CDOM": 110.12409360333699,
                "DOC": 128.6571530273242,
                "Color": 2189.8289105806725,
                "WQI": -0.38461472633709004
            }
        }
    },
    {
        "29-04-2018": {
            "min": {
                "Chl_a": 172199.32444667254,
                "Cya": 198.0239623092589,
                "Turb": 125.4492793256547,
                "CDOM": 4.181078298417933,
                "DOC": 10.55315983492376,
                "Color": 13.933657266877598,
                "WQI": -1.9754772330935748
            },
            "max": {
                "Chl_a": 3143.897618384732,
                "Cya": 290.1841840321924,
                "Turb": 41.33931080631766,
                "CDOM": 4.544165078806428,
                "DOC": 11.246864285288002,
                "Color": 15.84820809215695,
                "WQI": -1.3728813464195084
            },
            "mean": {
                "Chl_a": 19695.35364150861,
                "Cya": 245.82475812157068,
                "Turb": 69.65013446551269,
                "CDOM": 3.745918204865062,
                "DOC": 9.702701672742235,
                "Color": 11.756307675959318,
                "WQI": -1.8264986234264877
            },
            "stDev": {
                "Chl_a": 2.3907012170599464,
                "Cya": 0.05215526866655528,
                "Turb": 1.3221459792754509,
                "CDOM": 9.091111392039416,
                "DOC": 19.11049857639458,
                "Color": 46.30208940787025,
                "WQI": 0.008951797942518557
            }
        }
    },
    {
        "04-05-2018": {
            "min": {
                "Chl_a": 56.70264616550872,
                "Cya": 329.27345657826953,
                "Turb": 10.83581648533226,
                "CDOM": 6.625978734756191,
                "DOC": 15.005631864127054,
                "Color": 28.39363424180766,
                "WQI": -0.3729508279629292
            },
            "max": {
                "Chl_a": 16.336937960031406,
                "Cya": 2268.601246602353,
                "Turb": 6.170709301734276,
                "CDOM": 24.248428154927318,
                "DOC": 40.45778705013818,
                "Color": 211.02386045178312,
                "WQI": -0.16349043633536806
            },
            "mean": {
                "Chl_a": 27.466933437235205,
                "Cya": 1326.0303238680378,
                "Turb": 7.941217168602557,
                "CDOM": 19.088545589196187,
                "DOC": 33.69471769671549,
                "Color": 145.77321714477495,
                "WQI": -0.23695823656871023
            },
            "stDev": {
                "Chl_a": 4.089457390365832,
                "Cya": 54.462041464764944,
                "Turb": 2.4478764909542443,
                "CDOM": 84.10827527621603,
                "DOC": 104.7016415267795,
                "Color": 1443.616911924577,
                "WQI": 0.1308134869546085
            }
        }
    },
    {
        "09-05-2018": {
            "min": {
                "Chl_a": 274.69770366103256,
                "Cya": 769.496026019796,
                "Turb": 19.319969887786343,
                "CDOM": 21.760116666030427,
                "DOC": 37.243739455579245,
                "Color": 178.49721542903518,
                "WQI": -0.7277485277140444
            },
            "max": {
                "Chl_a": 24.09823263055947,
                "Cya": 1704.511545693048,
                "Turb": 7.47310436543174,
                "CDOM": 22.284930618003763,
                "DOC": 37.92852544450907,
                "Color": 185.19677766231084,
                "WQI": -0.14814815134198406
            },
            "mean": {
                "Chl_a": 79.59769086102837,
                "Cya": 1463.627226220203,
                "Turb": 12.384348604494644,
                "CDOM": 21.420817477408846,
                "DOC": 36.798947350920464,
                "Color": 174.21245728970234,
                "WQI": -0.3412066778736781
            },
            "stDev": {
                "Chl_a": 0.8674682294659529,
                "Cya": 1.8376234536482026,
                "Turb": -0.4274621498567557,
                "CDOM": 13.411770390177194,
                "DOC": 25.726063210444973,
                "Color": 84.46658669797478,
                "WQI": 0.33335093456175785
            }
        }
    },
    {
        "14-05-2018": {
            "min": {
                "Chl_a": 882.7231711530198,
                "Cya": 1039.5694626405825,
                "Turb": 28.185942664469408,
                "CDOM": 13.243573837915264,
                "DOC": 25.479045054224315,
                "Color": 82.8344594392578,
                "WQI": -2.156950744561097
            },
            "max": {
                "Chl_a": 537.5372904519802,
                "Cya": 1406.2715409651857,
                "Turb": 24.09596423012565,
                "CDOM": 16.026268132794442,
                "DOC": 29.47847216562756,
                "Color": 111.24182985856869,
                "WQI": -1.0023724310135234
            },
            "mean": {
                "Chl_a": 641.0963735570708,
                "Cya": 1157.55033316396,
                "Turb": 25.490117693318258,
                "CDOM": 14.101404989579526,
                "DOC": 26.731381671569995,
                "Color": 91.27518089406105,
                "WQI": -1.1802561502438178
            },
            "stDev": {
                "Chl_a": 125.65664976170993,
                "Cya": 0.7175651495584529,
                "Turb": 14.690990942678265,
                "CDOM": 33.543944257883254,
                "DOC": 51.84946032063787,
                "Color": 348.51442166075975,
                "WQI": -0.7405917006028719
            }
        }
    },
    {
        "29-05-2018": {
            "min": {
                "Chl_a": 11.988370456081698,
                "Cya": 146.80379884158728,
                "Turb": 5.221807386570775,
                "CDOM": 7.881766815150154,
                "DOC": 17.1347490412842,
                "Color": 37.132495954702684,
                "WQI": 0.1939393969041183
            },
            "max": {
                "Chl_a": 12.320885272844352,
                "Cya": 2537.710962638681,
                "Turb": 5.30271860380783,
                "CDOM": 31.52346996527022,
                "DOC": 49.44447926185645,
                "Color": 316.5974967043189,
                "WQI": -0.13245034909793085
            },
            "mean": {
                "Chl_a": 16.103890996997325,
                "Cya": 1183.8271567141253,
                "Turb": 6.12498834631863,
                "CDOM": 22.404842065580787,
                "DOC": 38.08445235631492,
                "Color": 186.7397226184843,
                "WQI": -0.1234323597925991
            },
            "stDev": {
                "Chl_a": 4.808756334628977,
                "Cya": 58.253939707570396,
                "Turb": 2.81889654429808,
                "CDOM": 84.89230597582987,
                "DOC": 105.44697925738687,
                "Color": 1464.4752298453336,
                "WQI": -0.24482374451364006
            }
        }
    },
    {
        "03-06-2018": {
            "min": {
                "Chl_a": 704.6756368120813,
                "Cya": 460.6632225176325,
                "Turb": 26.264477760155238,
                "CDOM": 6.881180229030342,
                "DOC": 15.445502068740533,
                "Color": 30.102083202706037,
                "WQI": -1.2950816301583177
            },
            "max": {
                "Chl_a": 16.571513870807525,
                "Cya": 3737.7016770274204,
                "Turb": 6.2162413531228475,
                "CDOM": 32.54805369447977,
                "DOC": 50.66844234916556,
                "Color": 332.647310615478,
                "WQI": -0.2184199254274625
            },
            "mean": {
                "Chl_a": 69.56967022236793,
                "Cya": 1774.8851354228473,
                "Turb": 11.753543277737307,
                "CDOM": 20.948879791611148,
                "DOC": 36.17750633489842,
                "Color": 168.31412561527122,
                "WQI": -0.42766136945110306
            },
            "stDev": {
                "Chl_a": 0.8918724340640531,
                "Cya": 101.08036089099754,
                "Turb": -0.3853276857149952,
                "CDOM": 100.0951147982018,
                "DOC": 119.59976291069137,
                "Color": 1889.2754387940724,
                "WQI": 0.045288780567215504
            }
        }
    },
    {
        "08-06-2018": {
            "min": {
                "Chl_a": 741.9886300857629,
                "Cya": 791.2295739104451,
                "Turb": 26.69491708511549,
                "CDOM": 11.326445847927152,
                "DOC": 22.608118636957148,
                "Color": 65.04511649646172,
                "WQI": -1.1082620807459835
            },
            "max": {
                "Chl_a": 21.622995000147103,
                "Cya": 3469.233774676291,
                "Turb": 7.096956556579175,
                "CDOM": 24.455638787573818,
                "DOC": 40.72183043802491,
                "Color": 213.81834298964014,
                "WQI": -0.22108701261191172
            },
            "mean": {
                "Chl_a": 45.755213471813825,
                "Cya": 2670.799166696637,
                "Turb": 9.923023073457944,
                "CDOM": 21.8892958227052,
                "DOC": 37.41265202244964,
                "Color": 180.13816787838206,
                "WQI": -0.3460772259601854
            },
            "stDev": {
                "Chl_a": 2.3638684662211866,
                "Cya": 18.783037641471292,
                "Turb": 1.3000839388953223,
                "CDOM": 37.661961080620074,
                "DOC": 56.648744273920705,
                "Color": 416.84156596140855,
                "WQI": 0.2297018559216023
            }
        }
    },
    {
        "13-06-2018": {
            "min": {
                "Chl_a": 868.4116078584714,
                "Cya": 278.08434300513585,
                "Turb": 28.042794952802083,
                "CDOM": 5.617307314000444,
                "DOC": 13.225818646640437,
                "Color": 21.99548854467296,
                "WQI": -1.2492402785203824
            },
            "max": {
                "Chl_a": 15.349673631305729,
                "Cya": 3621.220016702437,
                "Turb": 5.973550924952089,
                "CDOM": 31.636103082642727,
                "DOC": 49.57948362691896,
                "Color": 318.3481227745773,
                "WQI": -0.20519486752383395
            },
            "mean": {
                "Chl_a": 47.61817816687084,
                "Cya": 1532.8953564519036,
                "Turb": 10.089099780407444,
                "CDOM": 21.87969112747955,
                "DOC": 37.400101172654566,
                "Color": 180.01597776049522,
                "WQI": -0.35033807732293815
            },
            "stDev": {
                "Chl_a": 2.1977255202677504,
                "Cya": 130.10896996774898,
                "Turb": 1.159151166105615,
                "CDOM": 81.50827281438622,
                "DOC": 102.21812397998559,
                "Color": 1375.2070116294897,
                "WQI": 0.026186751427719857
            }
        }
    },
    {
        "23-06-2018": {
            "min": {
                "Chl_a": 117.97223428676512,
                "Cya": 336.2845432411974,
                "Turb": 14.356042698282717,
                "CDOM": 4.649301248564955,
                "DOC": 11.44526184017238,
                "Color": 16.418679920405733,
                "WQI": -0.3188405744937475
            },
            "max": {
                "Chl_a": 13.830156636034346,
                "Cya": 3068.8825476722077,
                "Turb": 5.650731020944469,
                "CDOM": 24.401744849876287,
                "DOC": 40.65320559331924,
                "Color": 213.0902699271029,
                "WQI": -0.12006382713274866
            },
            "mean": {
                "Chl_a": 30.525251157538044,
                "Cya": 1722.1912091877002,
                "Turb": 8.330409688953793,
                "CDOM": 20.26645232475579,
                "DOC": 35.27302409689431,
                "Color": 159.91280970086953,
                "WQI": -0.1904087855776345
            },
            "stDev": {
                "Chl_a": 4.176825053829145,
                "Cya": 60.10049498828807,
                "Turb": 2.4954213896330666,
                "CDOM": 57.57014241056112,
                "DOC": 78.35816902552223,
                "Color": 803.3484461976866,
                "WQI": 0.06197389768788012
            }
        }
    },
    {
        "03-07-2018": {
            "min": {
                "Chl_a": 152.25640462772813,
                "Cya": 660.2043833253945,
                "Turb": 15.743801972958707,
                "CDOM": 17.85134081865594,
                "DOC": 32.01202856300541,
                "Color": 131.4267791039835,
                "WQI": -0.5999999166368644
            },
            "max": {
                "Chl_a": 19.948693377871567,
                "Cya": 2530.936615472765,
                "Turb": 6.82387993395658,
                "CDOM": 24.003457031344748,
                "DOC": 40.144939836285936,
                "Color": 207.73691874957467,
                "WQI": -0.142227100011143
            },
            "mean": {
                "Chl_a": 51.38973203733146,
                "Cya": 1554.2596069620415,
                "Turb": 10.411010630650285,
                "CDOM": 21.383740138457274,
                "DOC": 36.75024197748459,
                "Color": 173.74646690630883,
                "WQI": -0.32010835515195746
            },
            "stDev": {
                "Chl_a": 0.8062290471026937,
                "Cya": 12.305735447891799,
                "Turb": -0.5372318929570836,
                "CDOM": 54.57232678344878,
                "DOC": 75.21921138918547,
                "Color": 739.5995237246866,
                "WQI": 0.37879125658894447
            }
        }
    },
    {
        "13-07-2018": {
            "min": {
                "Chl_a": 291.4660294936659,
                "Cya": 1582.8478174278268,
                "Turb": 19.709534703574434,
                "CDOM": 24.064695585945795,
                "DOC": 40.22321644487301,
                "Color": 208.5568882625937,
                "WQI": -1.0516792970349582
            },
            "max": {
                "Chl_a": 20.869376217606636,
                "Cya": 1993.3055912579266,
                "Turb": 6.97606934414456,
                "CDOM": 28.07008581164639,
                "DOC": 45.24745774058101,
                "Color": 264.6063887698553,
                "WQI": -0.2531646106835672
            },
            "mean": {
                "Chl_a": 79.33748533048556,
                "Cya": 1921.6562518325811,
                "Turb": 12.368752537730142,
                "CDOM": 26.680007389070667,
                "DOC": 43.524208898071784,
                "Color": 244.62301739255756,
                "WQI": -0.5295085511435346
            },
            "stDev": {
                "Chl_a": 0.022542632538092584,
                "Cya": 0.1765094880920276,
                "Turb": -4.029066792871484,
                "CDOM": 34.46591514392067,
                "DOC": 52.93547484284818,
                "Color": 363.4350844845413,
                "WQI": 0.12550653160876826
            }
        }
    },
    {
        "18-07-2018": {
            "min": {
                "Chl_a": 88.34479786690206,
                "Cya": 421.1660317990791,
                "Turb": 12.887796589611415,
                "CDOM": 14.998376709204038,
                "DOC": 28.021816509583484,
                "Color": 100.40595865921813,
                "WQI": -0.19720763168283256
            },
            "max": {
                "Chl_a": 0.25822390235375653,
                "Cya": 7611.469378941232,
                "Turb": -2.0060726601468994,
                "CDOM": 52.69240642899444,
                "DOC": 73.23009795159913,
                "Color": 700.5812314781414,
                "WQI": 0.3793217435083442
            },
            "mean": {
                "Chl_a": 11.400232789106134,
                "Cya": 1613.4387956762305,
                "Turb": 5.074497997072087,
                "CDOM": 21.056313489878278,
                "DOC": 36.31926087291476,
                "Color": 169.65053060507205,
                "WQI": -0.010900775523572758
            },
            "stDev": {
                "Chl_a": 0.07175083512349843,
                "Cya": 54.154004727839414,
                "Turb": -3.222595123532022,
                "CDOM": 67.5693256312038,
                "DOC": 88.56402668214926,
                "Color": 1029.0512544652693,
                "WQI": 0.4242511797499681
            }
        }
    },
    {
        "28-07-2018": {
            "min": {
                "Chl_a": 324.77635522011593,
                "Cya": 356.82785043244854,
                "Turb": 20.436301428694307,
                "CDOM": 10.031422854588193,
                "DOC": 20.60398456443397,
                "Color": 53.91237102666961,
                "WQI": -1.323144040869525
            },
            "max": {
                "Chl_a": 23.529232084121578,
                "Cya": 1990.613790494938,
                "Turb": 7.389283164054002,
                "CDOM": 29.796746791978244,
                "DOC": 47.36025831706728,
                "Color": 290.19003347586346,
                "WQI": -0.2077503043289599
            },
            "mean": {
                "Chl_a": 50.23486861819532,
                "Cya": 1173.7380608321605,
                "Turb": 10.31436825962518,
                "CDOM": 23.98312375670644,
                "DOC": 40.11893895473752,
                "Color": 207.4649134739133,
                "WQI": -0.344660353489311
            },
            "stDev": {
                "Chl_a": 5.770408515723452,
                "Cya": 58.22889057568985,
                "Turb": 3.2550051576176893,
                "CDOM": 55.355055409674605,
                "DOC": 76.042625202966,
                "Color": 756.0644481216808,
                "WQI": -0.00013939801281386273
            }
        }
    },
    {
        "02-08-2018": {
            "min": {
                "Chl_a": 37.977765046965395,
                "Cya": 400.4931991449764,
                "Turb": 9.169606778615528,
                "CDOM": 9.374811340093059,
                "DOC": 19.564770804573346,
                "Color": 48.55498488519349,
                "WQI": -0.05627715215355121
            },
            "max": {
                "Chl_a": 13.92613427276184,
                "Cya": 2194.732600840636,
                "Turb": 5.671884323878301,
                "CDOM": 25.190149411809568,
                "DOC": 41.65359656197039,
                "Color": 223.8281487192378,
                "WQI": -0.1202375131532608
            },
            "mean": {
                "Chl_a": 21.93693553804072,
                "Cya": 1256.4004717227258,
                "Turb": 7.146388779878527,
                "CDOM": 20.419244660175785,
                "DOC": 35.47614864928726,
                "Color": 161.78060692291623,
                "WQI": -0.15509161836735136
            },
            "stDev": {
                "Chl_a": 4.537930572384659,
                "Cya": 28.98625746772014,
                "Turb": 2.6844020943409808,
                "CDOM": 76.56778932764773,
                "DOC": 97.44674218908067,
                "Color": 1248.4855179723393,
                "WQI": 0.022401058542371767
            }
        }
    },
    {
        "07-08-2018": {
            "min": {
                "Chl_a": 1.4923239742036676,
                "Cya": 57.60839927278208,
                "Turb": 0.45274764855627936,
                "CDOM": 9.346055542866868,
                "DOC": 19.518874780611476,
                "Color": 48.324913166280844,
                "WQI": 0.46925563904539613
            },
            "max": {
                "Chl_a": 3.430058259185403,
                "Cya": 15480.217747919736,
                "Turb": 2.062129717245706,
                "CDOM": 19.173703034750893,
                "DOC": 33.80957648565423,
                "Color": 146.77988552899268,
                "WQI": 0.06722845055653204
            },
            "mean": {
                "Chl_a": 4.5996629441911825,
                "Cya": 621.535707359275,
                "Turb": 2.715575513023908,
                "CDOM": 14.906133705058535,
                "DOC": 27.88996623090761,
                "Color": 99.4528362668088,
                "WQI": 0.12270240252385013
            },
            "stDev": {
                "Chl_a": 4.584525522176329,
                "Cya": 121.7615164896943,
                "Turb": 2.7079604932602175,
                "CDOM": 24.710494110505806,
                "DOC": 41.04586507103212,
                "Color": 217.27313790821964,
                "WQI": -0.04645455915024441
            }
        }
    },
    {
        "17-08-2018": {
            "min": {
                "Chl_a": 62.260314925366465,
                "Cya": 189.8050051336858,
                "Turb": 11.249505726645005,
                "CDOM": 5.8686257493994844,
                "DOC": 13.675853915204312,
                "Color": 23.535409792895887,
                "WQI": -0.15280459408261793
            },
            "max": {
                "Chl_a": 37.569498578834384,
                "Cya": 1594.390961327214,
                "Turb": 9.126981616613762,
                "CDOM": 24.81550809390415,
                "DOC": 41.17915536271808,
                "Color": 218.70237947485262,
                "WQI": -0.2572215296586424
            },
            "mean": {
                "Chl_a": 38.501029525082615,
                "Cya": 731.4983601552912,
                "Turb": 9.223741235744786,
                "CDOM": 16.707368764463094,
                "DOC": 30.43153790965738,
                "Color": 118.63543915333355,
                "WQI": -0.12774724052871536
            },
            "stDev": {
                "Chl_a": 18.6234121565049,
                "Cya": 18.78236470974033,
                "Turb": 6.595327111154817,
                "CDOM": 60.26123119558462,
                "DOC": 81.14328648315292,
                "Color": 862.142719144444,
                "WQI": -0.20656343009694025
            }
        }
    },
    {
        "22-08-2018": {
            "min": {
                "Chl_a": 70.95107675603745,
                "Cya": 214.33507650790565,
                "Turb": 11.844311747022893,
                "CDOM": 12.199741477862235,
                "DOC": 23.9290273368306,
                "Color": 72.96026468924055,
                "WQI": -0.13661204688674888
            },
            "max": {
                "Chl_a": 41.25911051835441,
                "Cya": 1341.3787530550437,
                "Turb": 9.500342250341717,
                "CDOM": 24.690115736463994,
                "DOC": 41.01998412809905,
                "Color": 216.99617162390743,
                "WQI": -0.385273915039526
            },
            "mean": {
                "Chl_a": 47.837710529118986,
                "Cya": 735.2883179219082,
                "Turb": 10.108349188369207,
                "CDOM": 16.25446483137543,
                "DOC": 29.798831820398398,
                "Color": 113.70025626338986,
                "WQI": -0.2732236573725943
            },
            "stDev": {
                "Chl_a": 5.359210259086056,
                "Cya": 9.392078898883167,
                "Turb": 3.075723039550083,
                "CDOM": 97.90743023331724,
                "DOC": 117.5961726372785,
                "Color": 1825.8169737647281,
                "WQI": -0.1818640123640863
            }
        }
    },
    {
        "01-09-2018": {
            "min": {
                "Chl_a": 60.35471417560024,
                "Cya": 379.94213810088064,
                "Turb": 11.110884008348243,
                "CDOM": 23.660260156294832,
                "DOC": 39.70538242626851,
                "Color": 203.16275863492504,
                "WQI": -0.20647772180248397
            },
            "max": {
                "Chl_a": 46.225467083871024,
                "Cya": 1340.2705543956206,
                "Turb": 9.965413832695056,
                "CDOM": 25.858700096891972,
                "DOC": 42.496139128564806,
                "Color": 233.0787976934295,
                "WQI": -0.4203655816377751
            },
            "mean": {
                "Chl_a": 66.0194726900636,
                "Cya": 816.5056851154429,
                "Turb": 11.513936462106457,
                "CDOM": 18.954009949728672,
                "DOC": 33.51301221025902,
                "Color": 144.18782979829757,
                "WQI": -0.3720478169252142
            },
            "stDev": {
                "Chl_a": 6.752336116505213,
                "Cya": 5.401561765354073,
                "Turb": 3.6474677465241614,
                "CDOM": 20.023700370667864,
                "DOC": 34.94956213005136,
                "Color": 156.96110043040167,
                "WQI": -0.5271726566828175
            }
        }
    },
    {
        "06-09-2018": {
            "min": {
                "Chl_a": 113.79273279153655,
                "Cya": 249.48053611164386,
                "Turb": 14.166979779611573,
                "CDOM": 20.662740234214922,
                "DOC": 35.79911777927531,
                "Color": 164.77299309947952,
                "WQI": -0.052924806984037544
            },
            "max": {
                "Chl_a": 72.07663614642662,
                "Cya": 1215.9529689716862,
                "Turb": 11.91729917786375,
                "CDOM": 26.074844399900943,
                "DOC": 42.767433507022886,
                "Color": 236.09777075954074,
                "WQI": -0.4771863489489581
            },
            "mean": {
                "Chl_a": 98.74371576681595,
                "Cya": 705.0758925348154,
                "Turb": 13.440036166913032,
                "CDOM": 18.045506584909134,
                "DOC": 32.277881417493475,
                "Color": 133.64345401147162,
                "WQI": -0.38251917612579117
            },
            "stDev": {
                "Chl_a": 5.352004659309707,
                "Cya": 4.4668101528569135,
                "Turb": 3.072491236503505,
                "CDOM": 61.14869301739,
                "DOC": 82.05528779594955,
                "Color": 881.8515274937179,
                "WQI": -0.4355810725605054
            }
        }
    },
    {
        "11-09-2018": {
            "min": {
                "Chl_a": 155.81124195321982,
                "Cya": 611.37290083957,
                "Turb": 15.873835491586252,
                "CDOM": 13.507749387009211,
                "DOC": 25.86669347523061,
                "Color": 85.40296742900425,
                "WQI": -0.6861538126482774
            },
            "max": {
                "Chl_a": 36.792734574891014,
                "Cya": 949.5457139046077,
                "Turb": 9.044919530161163,
                "CDOM": 23.124644931828016,
                "DOC": 39.01636505882338,
                "Color": 196.09623094104788,
                "WQI": -0.3296500299189506
            },
            "mean": {
                "Chl_a": 79.01310601632406,
                "Cya": 805.5715287950561,
                "Turb": 12.34925651521182,
                "CDOM": 17.617790971210795,
                "DOC": 31.69134663994812,
                "Color": 128.77787675634806,
                "WQI": -0.47390029396198186
            },
            "stDev": {
                "Chl_a": 0.07054137964538931,
                "Cya": 0.4894056988885367,
                "Turb": -3.236232158913126,
                "CDOM": 160.26777970145105,
                "DOC": 171.40388152854996,
                "Color": 3911.691260452247,
                "WQI": -0.025565536973852696
            }
        }
    },
    {
        "16-09-2018": {
            "min": {
                "Chl_a": 64.27371137671116,
                "Cya": 245.98126666766015,
                "Turb": 11.392570945514183,
                "CDOM": 21.351588449984114,
                "DOC": 36.70799091384877,
                "Color": 173.34273942377934,
                "WQI": 0.10628027191736983
            },
            "max": {
                "Chl_a": 55.243825272999935,
                "Cya": 1129.053489273113,
                "Turb": 10.722238532314822,
                "CDOM": 27.41247162456787,
                "DOC": 44.43479553406474,
                "Color": 255.08366011028951,
                "WQI": -0.35606668417543313
            },
            "mean": {
                "Chl_a": 69.23468725426882,
                "Cya": 641.2319112157837,
                "Turb": 11.731330117021244,
                "CDOM": 17.834287162714304,
                "DOC": 31.98864616129794,
                "Color": 131.23271384759468,
                "WQI": -0.26000963827562423
            },
            "stDev": {
                "Chl_a": 7.88904169636037,
                "Cya": 7.3816698313825135,
                "Turb": 4.05176607320706,
                "CDOM": 62.1841300547591,
                "DOC": 83.11542654344612,
                "Color": 905.0447320297976,
                "WQI": -0.5617492156331477
            }
        }
    },
    {
        "21-09-2018": {
            "min": {
                "Chl_a": 104.60903379190245,
                "Cya": 484.98389121882997,
                "Turb": 13.732588335824392,
                "CDOM": 21.664404514524872,
                "DOC": 37.11843549042385,
                "Color": 177.2848161903201,
                "WQI": -0.11855663446547104
            },
            "max": {
                "Chl_a": 50.21163836246689,
                "Cya": 1454.9340515120182,
                "Turb": 10.312407350365497,
                "CDOM": 25.012255389738037,
                "DOC": 41.428522447007566,
                "Color": 221.38900843119325,
                "WQI": -0.4406332246348036
            },
            "mean": {
                "Chl_a": 79.04386503887775,
                "Cya": 991.8326840020959,
                "Turb": 12.351107771139478,
                "CDOM": 19.708563493099593,
                "DOC": 34.52826709618515,
                "Color": 153.1583065932761,
                "WQI": -0.40617224159500614
            },
            "stDev": {
                "Chl_a": 3.230990649771047,
                "Cya": 7.566953893466938,
                "Turb": 1.9348391371806928,
                "CDOM": 48.221767294994265,
                "DOC": 68.43092557825481,
                "Color": 610.839364042613,
                "WQI": -0.572233781966418
            }
        }
    },
    {
        "01-10-2018": {
            "min": {
                "Chl_a": 104.3317411288908,
                "Cya": 359.742511185824,
                "Turb": 13.719036854502924,
                "CDOM": 27.3031297608772,
                "DOC": 44.299230988561504,
                "Color": 253.5122918664717,
                "WQI": -0.4065041450670492
            },
            "max": {
                "Chl_a": 82.6507556605486,
                "Cya": 3567.7245446164106,
                "Turb": 12.564559670686563,
                "CDOM": 38.450412698103946,
                "DOC": 57.55318492803945,
                "Color": 430.41036251873317,
                "WQI": -0.6237970375760882
            },
            "mean": {
                "Chl_a": 79.88624833735301,
                "Cya": 1150.7862337728145,
                "Turb": 12.401599591730797,
                "CDOM": 24.111779330201667,
                "DOC": 40.28336813445364,
                "Color": 209.1881037037078,
                "WQI": -0.3406797028658363
            },
            "stDev": {
                "Chl_a": 132.19058022691635,
                "Cya": 26.206428253049015,
                "Turb": 14.963968283491628,
                "CDOM": 27.055503487348346,
                "DOC": 43.99174441674179,
                "Color": 249.96631725243765,
                "WQI": -0.7432961732123748
            }
        }
    },
    {
        "11-10-2018": {
            "min": {
                "Chl_a": 79.47166670905607,
                "Cya": 585.6343584737762,
                "Turb": 12.376799791383739,
                "CDOM": 15.58331935220063,
                "DOC": 28.853538615674697,
                "Color": 106.52428493839365,
                "WQI": -0.2902033740115327
            },
            "max": {
                "Chl_a": 78.51036921762214,
                "Cya": 834.0526435459161,
                "Turb": 12.318922405605942,
                "CDOM": 15.260316513540136,
                "DOC": 28.395192419318178,
                "Color": 103.12996364869859,
                "WQI": -0.5024015956983308
            },
            "mean": {
                "Chl_a": 96.0170031619761,
                "Cya": 718.2791212551244,
                "Turb": 13.29959926055028,
                "CDOM": 14.649271560788138,
                "DOC": 27.5217948052991,
                "Color": 96.81571991333908,
                "WQI": -0.4092717929872459
            },
            "stDev": {
                "Chl_a": 55.57003619574375,
                "Cya": 0.2370983777493673,
                "Turb": 10.747828561926287,
                "CDOM": 10.754146572248917,
                "DOC": 21.72948959747988,
                "Color": 60.03446412349848,
                "WQI": -0.7261297809618037
            }
        }
    },
    {
        "26-10-2018": {
            "min": {
                "Chl_a": 534.8133745019727,
                "Cya": 347.6899342618727,
                "Turb": 24.056680604926132,
                "CDOM": 13.08998524024954,
                "DOC": 25.252834526590714,
                "Color": 81.35393491314699,
                "WQI": -0.9372195121991964
            },
            "max": {
                "Chl_a": 677.206900291878,
                "Cya": 568.7264620110332,
                "Turb": 25.936600144156316,
                "CDOM": 9.371539603660208,
                "DOC": 19.559550584831566,
                "Color": 48.52878865541252,
                "WQI": -0.9698795118197604
            },
            "mean": {
                "Chl_a": 837.9348291579983,
                "Cya": 503.57787611343923,
                "Turb": 27.73199093756194,
                "CDOM": 9.822442680750285,
                "DOC": 20.27502130308771,
                "Color": 52.185832310742725,
                "WQI": -1.1561820964944967
            },
            "stDev": {
                "Chl_a": 1120.156400053577,
                "Cya": 0.5727292524846949,
                "Turb": 30.340887732761544,
                "CDOM": 3.6224157439107674,
                "DOC": 9.457176316933134,
                "Color": 11.162464598531061,
                "WQI": -1.0537286793155256
            }
        }
    },
    {
        "31-10-2018": {
            "min": {
                "Chl_a": 454.5349985779009,
                "Cya": 308.9402412884181,
                "Turb": 22.8254314311638,
                "CDOM": 9.14958027043577,
                "DOC": 19.204391326294132,
                "Color": 46.763300961102274,
                "WQI": -1.0347823847557247
            },
            "max": {
                "Chl_a": 99.09676718566855,
                "Cya": 1808.9383399557796,
                "Turb": 13.458007374335825,
                "CDOM": 27.72917174303485,
                "DOC": 44.826731587908135,
                "Color": 259.6543175700779,
                "WQI": -0.6099584889063835
            },
            "mean": {
                "Chl_a": 147.826964341578,
                "Cya": 840.6149446143296,
                "Turb": 15.578566939659112,
                "CDOM": 16.713602416412925,
                "DOC": 30.440217909420255,
                "Color": 118.70388132063516,
                "WQI": -0.6340209006930235
            },
            "stDev": {
                "Chl_a": 3.6649942604920964,
                "Cya": 14.356526825613368,
                "Turb": 2.2054504593384037,
                "CDOM": 126.29320232014874,
                "DOC": 142.86313582004323,
                "Color": 2706.437399916215,
                "WQI": -0.3506788314475373
            }
        }
    },
    {
        "20-12-2018": {
            "min": {
                "Chl_a": 247.3692805229938,
                "Cya": 192.4604872658339,
                "Turb": 18.645195872183173,
                "CDOM": 10.753920383207912,
                "DOC": 21.729140194498196,
                "Color": 60.032511923383844,
                "WQI": -0.6132073822239541
            },
            "max": {
                "Chl_a": 140.4258814316094,
                "Cya": 623.9148283959962,
                "Turb": 15.294038992460319,
                "CDOM": 12.764764289971467,
                "DOC": 24.771760754865984,
                "Color": 78.25022501029416,
                "WQI": -0.6738816347864062
            },
            "mean": {
                "Chl_a": 228.40425482529997,
                "Cya": 503.1044517379247,
                "Turb": 18.143455115961643,
                "CDOM": 15.466442978768224,
                "DOC": 28.687949880231496,
                "Color": 105.29159262368657,
                "WQI": -0.8284042258061055
            },
            "stDev": {
                "Chl_a": 20.251199067674367,
                "Cya": 1.2211459814018502,
                "Turb": 6.874452003510661,
                "CDOM": 17.27147850875398,
                "DOC": 31.213982263310196,
                "Color": 124.88523611097027,
                "WQI": -0.4013451434017192
            }
        }
    }
]